MANIFEST.in
README
requirements.txt
setup.py
moz_addon_packager.egg-info/PKG-INFO
moz_addon_packager.egg-info/SOURCES.txt
moz_addon_packager.egg-info/dependency_links.txt
moz_addon_packager.egg-info/not-zip-safe
moz_addon_packager.egg-info/top_level.txt
packager/__init__.py
packager/main.py
packager/resources/chrome.manifest
packager/resources/install.rdf
packager/resources/chrome/content/about.xul
packager/resources/chrome/content/ff-overlay.js
packager/resources/chrome/content/ff-overlay.xul
packager/resources/chrome/content/ff-sidebar.js
packager/resources/chrome/content/ff-sidebar.xul
packager/resources/chrome/content/options.xul
packager/resources/chrome/content/overlay.js
packager/resources/chrome/locale/en-US/about.dtd
packager/resources/chrome/locale/en-US/options.dtd
packager/resources/chrome/locale/en-US/overlay.dtd
packager/resources/chrome/locale/en-US/overlay.properties
packager/resources/chrome/skin/overlay.css
packager/resources/chrome/skin/toolbar-button.png
packager/resources/defaults/preferences/prefs.js