Metadata-Version: 1.0
Name: moz-addon-packager
Version: 1.0.1
Summary: Creates addons for Mozilla products.
Home-page: http://github.com/mattbasta/addon-packager
Author: Matt Basta
Author-email: me@mattbasta.com
License: BSD
Platform: UNKNOWN
Classifier: Development Status :: 4 - Beta
Classifier: Environment :: Web Environment
Classifier: Intended Audience :: Developers
Classifier: License :: OSI Approved :: BSD License
Classifier: Operating System :: OS Independent
Classifier: Programming Language :: Python
Classifier: Topic :: Software Development :: Libraries :: Python Modules
